{"Columns":[{"$type":"Forguncy.Model.Tables.BindingColumn, ServerDesignerCommon","Required":true,"Unique":true,"DatabaseColumnType":"varchar","MaxLength":-1,"Name":"UtilityId","ColumnType":"System.String, mscorlib, Version=4.0.0.0, Culture=neutral, PublicKeyToken=b77a5c561934e089"},{"$type":"Forguncy.Model.Tables.BindingColumn, ServerDesignerCommon","DatabaseColumnType":"varchar","MaxLength":-1,"Name":"UtilityClassificationCode","ColumnType":"System.String, mscorlib, Version=4.0.0.0, Culture=neutral, PublicKeyToken=b77a5c561934e089"},{"$type":"Forguncy.Model.Tables.BindingColumn, ServerDesignerCommon","DatabaseColumnType":"varchar","MaxLength":-1,"Name":"UtilityClassificationName","ColumnType":"System.String, mscorlib, Version=4.0.0.0, Culture=neutral, PublicKeyToken=b77a5c561934e089"},{"$type":"Forguncy.Model.Tables.BindingColumn, ServerDesignerCommon","DatabaseColumnType":"varchar","MaxLength":-1,"Name":"UtilitySubClassificationCode","ColumnType":"System.String, mscorlib, Version=4.0.0.0, Culture=neutral, PublicKeyToken=b77a5c561934e089"},{"$type":"Forguncy.Model.Tables.BindingColumn, ServerDesignerCommon","DatabaseColumnType":"varchar","MaxLength":-1,"Name":"UtilityName","ColumnType":"System.String, mscorlib, Version=4.0.0.0, Culture=neutral, PublicKeyToken=b77a5c561934e089"},{"$type":"Forguncy.Model.Tables.BindingColumn, ServerDesignerCommon","DatabaseColumnType":"char","MaxLength":-1,"Name":"CylinderFlag","ColumnType":"System.String, mscorlib, Version=4.0.0.0, Culture=neutral, PublicKeyToken=b77a5c561934e089"},{"$type":"Forguncy.Model.Tables.BindingColumn, ServerDesignerCommon","DatabaseColumnType":"char","MaxLength":-1,"Name":"delete_flag","ColumnType":"System.String, mscorlib, Version=4.0.0.0, Culture=neutral, PublicKeyToken=b77a5c561934e089"}],"ExternalDatabaseInfo":{"SourceConnectString":"Data Source=rds-commondb-poc-zeon-db-001.cjzyjlprofpu.ap-northeast-1.rds.amazonaws.com;Initial Catalog=LOCATION_MST;Persist Security Info=True;User ID=CreditMgmt;Password=6gSg@Ykst","SourceTableName":"M_Utility","SourceTableSchema":"dbo","DataBaseType":1,"UserSetQueryColumns":[]},"PrimaryKey":["UtilityId"],"Name":"M_Utility","Relations":[]}